shiva/__init__.py
shiva/cli.py
shiva/si_format.py
shiva_si-0.1.dist-info/METADATA
shiva_si-0.1.dist-info/WHEEL
shiva_si-0.1.dist-info/top_level.txt
shiva_si-0.1.dist-info/RECORD
