Metadata-Version: 2.1
Name: shiva-si
Version: 0.1
Summary: Dataset-agnostic model saving and loading format (.si) for AI/ML pipelines
Home-page: https://github.com/siddiquesh/shiva-si
Author: Siddique Shiva
Author-email: Siddique Shiva <easwararaj05687@gmail.com>
License: Proprietary
Keywords: model saving,torch,tensorflow,onnx,machine learning,serialization,.si format
Classifier: Programming Language :: Python :: 3
Classifier: License :: Other/Proprietary License
Classifier: Operating System :: OS Independent
Requires-Python: >=3.7
Requires-Dist: torch>=1.12.0
Requires-Dist: tensorflow==2.10.1
Requires-Dist: onnx>=1.12.0
Requires-Dist: psutil
Requires-Dist: cython
Requires-Dist: numpy<2.0
